geofeather/__init__.py
geofeather/core.py
geofeather/pygeos.py
geofeather-0.3.0.dist-info/LICENSE
geofeather-0.3.0.dist-info/METADATA
geofeather-0.3.0.dist-info/WHEEL
geofeather-0.3.0.dist-info/top_level.txt
geofeather-0.3.0.dist-info/RECORD
