Metadata-Version: 2.1
Name: geofeather
Version: 0.3.0
Summary: Fast file-based format for geometries with Geopandas
Home-page: https://github.com/brendan-ward/geofeather
Author: Brendan C. Ward
Author-email: bcward@astutespruce.com
License: MIT
Platform: UNKNOWN
Requires-Dist: feather-format
Requires-Dist: geopandas
